easy_monitor.py
easy_monitor-0.2.dist-info/METADATA
easy_monitor-0.2.dist-info/WHEEL
easy_monitor-0.2.dist-info/top_level.txt
easy_monitor-0.2.dist-info/RECORD
