Metadata-Version: 2.1
Name: easy-monitor
Version: 0.2
Summary: A module for monitoring variable changes
Home-page: https://github.com/SanLiWuXun/easy_monitor
Author: Feifei Song
Author-email: songfeifei@tsinghua.org.cn
License: MIT
Platform: UNKNOWN
Requires: matplotlib
Requires: numpy
